djangocms_style/__init__.py
djangocms_style/cms_plugins.py
djangocms_style/models.py
djangocms_style/locale/af/LC_MESSAGES/django.mo
djangocms_style/locale/af/LC_MESSAGES/django.po
djangocms_style/locale/ar/LC_MESSAGES/django.mo
djangocms_style/locale/ar/LC_MESSAGES/django.po
djangocms_style/locale/be/LC_MESSAGES/django.mo
djangocms_style/locale/be/LC_MESSAGES/django.po
djangocms_style/locale/bg/LC_MESSAGES/django.mo
djangocms_style/locale/bg/LC_MESSAGES/django.po
djangocms_style/locale/ca/LC_MESSAGES/django.mo
djangocms_style/locale/ca/LC_MESSAGES/django.po
djangocms_style/locale/cmn/LC_MESSAGES/django.mo
djangocms_style/locale/cmn/LC_MESSAGES/django.po
djangocms_style/locale/cs/LC_MESSAGES/django.mo
djangocms_style/locale/cs/LC_MESSAGES/django.po
djangocms_style/locale/da/LC_MESSAGES/django.mo
djangocms_style/locale/da/LC_MESSAGES/django.po
djangocms_style/locale/de/LC_MESSAGES/django.mo
djangocms_style/locale/de/LC_MESSAGES/django.po
djangocms_style/locale/el/LC_MESSAGES/django.mo
djangocms_style/locale/el/LC_MESSAGES/django.po
djangocms_style/locale/en/LC_MESSAGES/django.mo
djangocms_style/locale/en/LC_MESSAGES/django.po
djangocms_style/locale/es/LC_MESSAGES/django.mo
djangocms_style/locale/es/LC_MESSAGES/django.po
djangocms_style/locale/es_AR/LC_MESSAGES/django.mo
djangocms_style/locale/es_AR/LC_MESSAGES/django.po
djangocms_style/locale/es_BO/LC_MESSAGES/django.mo
djangocms_style/locale/es_BO/LC_MESSAGES/django.po
djangocms_style/locale/et/LC_MESSAGES/django.mo
djangocms_style/locale/et/LC_MESSAGES/django.po
djangocms_style/locale/eu/LC_MESSAGES/django.mo
djangocms_style/locale/eu/LC_MESSAGES/django.po
djangocms_style/locale/fa/LC_MESSAGES/django.mo
djangocms_style/locale/fa/LC_MESSAGES/django.po
djangocms_style/locale/fi/LC_MESSAGES/django.mo
djangocms_style/locale/fi/LC_MESSAGES/django.po
djangocms_style/locale/fr/LC_MESSAGES/django.mo
djangocms_style/locale/fr/LC_MESSAGES/django.po
djangocms_style/locale/ga/LC_MESSAGES/django.mo
djangocms_style-3.1.0.dist-info/LICENSE
djangocms_style-3.1.0.dist-info/METADATA
djangocms_style-3.1.0.dist-info/WHEEL
djangocms_style-3.1.0.dist-info/top_level.txt
djangocms_style-3.1.0.dist-info/RECORD
